cert_tools/__init__.py
cert_tools/create_issuer.py
cert_tools/create_revocation_addresses.py
cert_tools/create_v1_2_certificate_template.py
cert_tools/create_v2_certificate_template.py
cert_tools/create_v2_issuer.py
cert_tools/create_v3_certificate_template.py
cert_tools/extract_links.py
cert_tools/helpers.py
cert_tools/instantiate_v1_2_certificate_batch.py
cert_tools/instantiate_v2_certificate_batch.py
cert_tools/instantiate_v3_certificate_batch.py
cert_tools/jsonpath_helpers.py
tests/__init__.py
tests/test_cert_tools.py
tests/test_create_v3_certificate_template.py
cert_tools-3.0.2.dist-info/LICENSE
cert_tools-3.0.2.dist-info/METADATA
cert_tools-3.0.2.dist-info/WHEEL
cert_tools-3.0.2.dist-info/entry_points.txt
cert_tools-3.0.2.dist-info/top_level.txt
cert_tools-3.0.2.dist-info/RECORD
