Metadata-Version: 2.1
Name: cert-tools
Version: 3.0.2
Summary: creates blockchain certificates
Home-page: https://github.com/blockchain-certificates/cert-tools
Author: Blockcerts
Author-email: info@blockcerts.org
License: MIT
Platform: UNKNOWN
Requires-Dist: cert-core (>=2.1.10)
Requires-Dist: cert-schema (>=3.1.0)
Requires-Dist: configargparse (>=0.13.0)
Requires-Dist: jsonpath-rw (>=1.4.0)
Requires-Dist: pycoin (>=0.80)
Requires-Dist: tox (>=3.0.0)
